README.rst
setup.py
hello/__init__.py
hello/maiusculo.py
hello/minusculo.py
hello_pylab_example.egg-info/PKG-INFO
hello_pylab_example.egg-info/SOURCES.txt
hello_pylab_example.egg-info/dependency_links.txt
hello_pylab_example.egg-info/not-zip-safe
hello_pylab_example.egg-info/top_level.txt