Metadata-Version: 1.0
Name: hello-pylab-example
Version: 0.0.1
Summary: Simplesmente Hi
Home-page: http://github.com/seuprojeto/hello
Author: Seu Nome
Author-email: seu@email.com
License: GPL
Platform: UNKNOWN
